jal_bitbucket/__init__.py
jal_bitbucket/bitbucket.py
jal_bitbucket-0.0.2.dist-info/LICENSE
jal_bitbucket-0.0.2.dist-info/METADATA
jal_bitbucket-0.0.2.dist-info/WHEEL
jal_bitbucket-0.0.2.dist-info/top_level.txt
jal_bitbucket-0.0.2.dist-info/RECORD
